{
  "Users": [
    {
      "Id": 1,
      "Username": "Cristian",
      "Email": "josan.c2003@gmail.com",
      "Password": "15438",
      "Role": null
    },
    {
      "Id": 2,
      "Username": "Danielle",
      "Email": "danielle23@gmail.com",
      "Password": "danielle123",
      "Role": null
    },
    {
      "Id": 3,
      "Username": "Johnny",
      "Email": "johnny@gmail.com",
      "Password": "johnny123",
      "Role": "Administrator"
    },
    {
      "Id": 4,
      "Username": "abecedar",
      "Email": "abecedar@gmail.com",
      "Password": "abecedar",
      "Role": "User"
    }
  ],
  "Posts": [
    {
      "Id": 1,
      "Owner": {
        "Id": 1,
        "Username": "Cristian",
        "Email": "josan.c2003@gmail.com",
        "Password": "15438",
        "Role": null
      },
      "Title": "Learn Angular \u002B TypeScript",
      "Body": "Should watch module 2 of the course"
    }
  ],
  "Comments": [
    {
      "Id": 1,
      "Content": "Good luck, Cristian!",
      "Owner": {
        "Id": 2,
        "Username": "Danielle",
        "Email": "danielle23@gmail.com",
        "Password": "danielle123",
        "Role": null
      },
      "Post": {
        "Id": 1,
        "Owner": {
          "Id": 1,
          "Username": "Cristian",
          "Email": "josan.c2003@gmail.com",
          "Password": "15438",
          "Role": null
        },
        "Title": "Learn Angular \u002B TypeScript",
        "Body": "Should watch module 2 of the course"
      },
      "Date": "2023-09-28T14:35:22.3957436+02:00"
    }
  ]
}